Metadata-Version: 2.1
Name: binom-probab
Version: 0.2
Summary: Gaussian distributions
Home-page: UNKNOWN
License: UNKNOWN
Platform: UNKNOWN
